Workbook

Sheet 1. Cover
B2: WASHINGTON SQUARE RESEARCH PARTNERS
B3: NYU MSFE Equity Research | Equity Research Report — AVGO
B4: Authors: Tanishk Yadav | Martin Baretto | Ramana Sriram
B5: Report date: 25 April 2026
B7: Recommendation | C7: BUY
B8: Spot price (USD) | C8: 399.83
B9: 12-month price target (USD) | C9: 475
B10: Implied upside | C10: =C9/C8-1
B11: Market cap ($mn) | C11: 2001630
B12: Diluted shares (mn) | C12: 4969
B13: 52-week range | C13: $138.10 – $422.76
B15: Workbook Contents
B16: 1. Cover | C16: This page
B17: 2. Assumptions | C17: Key drivers, growth rates, margins
B18: 3. Income Statement | C18: FY23A – FY30E with formulas
B19: 4. DCF | C19: FCFF + Gordon terminal value
B20: 5. WACC | C20: Cost of capital build
B21: 6. Sensitivity | C21: WACC × terminal-g grid
B22: 7. Comps | C22: Peer trading multiples
B23: 8. SOTP | C23: Sum-of-the-parts by segment
B24: 9. Monte Carlo | C24: Stochastic distribution summary
B25: 10. Football Field | C25: Synthesis of valuation methods
B28: Color coding (industry standard)
B29: Blue text | C29: Hardcoded inputs
B30: Black text | C30: Formulas / calculations
B31: Green text | C31: Cross-sheet links
B32: Yellow fill | C32: Key assumptions

Sheet 2. Assumptions
B2: OPERATING ASSUMPTIONS
C4: FY23A | D4: FY24A | E4: FY25A | F4: FY26E | G4: FY27E | H4: FY28E | I4: FY29E | J4: FY30E
B5: Revenue ($mn)
B6: AI Semiconductor | C6: 4000 | D6: 12200 | E6: 24500 | F6: 60000 | G6: 115000 | H6: 165000 | I6: 205000 | J6: 235000
B7: Non-AI Semiconductor | C7: 21800 | D7: 18500 | E7: 15500 | F7: 16500 | G7: 17000 | H7: 17750 | I7: 18500 | J7: 19250
B8: Infrastructure Software | C8: 10000 | D8: 20800 | E8: 23900 | F8: 28500 | G8: 31000 | H8: 33500 | I8: 35500 | J8: 37500
B9: Total Revenue (formula) | C9: =SUM(C6:C8) | D9: =SUM(D6:D8) | E9: =SUM(E6:E8) | F9: =SUM(F6:F8) | G9: =SUM(G6:G8) | H9: =SUM(H6:H8) | I9: =SUM(I6:I8) | J9: =SUM(J6:J8)
B10: Revenue growth YoY | D10: =D9/C9-1 | E10: =E9/D9-1 | F10: =F9/E9-1 | G10: =G9/F9-1 | H10: =H9/G9-1 | I10: =I9/H9-1 | J10: =J9/I9-1
B12: MARGIN & CAPITAL ASSUMPTIONS
B13: Gross margin | C13: 0.696 | D13: 0.626 | E13: 0.745 | F13: 0.77 | G13: 0.775 | H13: 0.78 | I13: 0.78 | J13: 0.78
B14: Opex % of revenue | C14: 0.085 | D14: 0.09 | E14: 0.085 | F14: 0.085 | G14: 0.075 | H14: 0.072 | I14: 0.07 | J14: 0.069
B15: D&A % of revenue | C15: 0.03 | D15: 0.025 | E15: 0.02 | F15: 0.012 | G15: 0.01 | H15: 0.009 | I15: 0.009 | J15: 0.008
B16: Capex % of revenue | C16: 0.018 | D16: 0.02 | E16: 0.012 | F16: 0.012 | G16: 0.01 | H16: 0.01 | I16: 0.01 | J16: 0.01
B17: NWC change % of revenue | C17: 0.008 | D17: 0.01 | E17: 0.009 | F17: 0.01 | G17: 0.012 | H17: 0.01 | I17: 0.008 | J17: 0.008
B18: Effective tax rate | C18: 0.18 | D18: 0.18 | E18: 0.17 | F18: 0.18 | G18: 0.18 | H18: 0.18 | I18: 0.18 | J18: 0.18

Sheet 3. Income Statement
B2: INCOME STATEMENT — FY23A – FY30E ($ in millions)
C4: FY23A | D4: FY24A | E4: FY25A | F4: FY26E | G4: FY27E | H4: FY28E | I4: FY29E | J4: FY30E
B6: AI Semiconductor revenue | C6: ='2. Assumptions'!C6 | D6: ='2. Assumptions'!D6 | E6: ='2. Assumptions'!E6 | F6: ='2. Assumptions'!F6 | G6: ='2. Assumptions'!G6 | H6: ='2. Assumptions'!H6 | I6: ='2. Assumptions'!I6 | J6: ='2. Assumptions'!J6
B7: Non-AI Semi revenue | C7: ='2. Assumptions'!C7 | D7: ='2. Assumptions'!D7 | E7: ='2. Assumptions'!E7 | F7: ='2. Assumptions'!F7 | G7: ='2. Assumptions'!G7 | H7: ='2. Assumptions'!H7 | I7: ='2. Assumptions'!I7 | J7: ='2. Assumptions'!J7
B8: Infrastructure Software revenue | C8: ='2. Assumptions'!C8 | D8: ='2. Assumptions'!D8 | E8: ='2. Assumptions'!E8 | F8: ='2. Assumptions'!F8 | G8: ='2. Assumptions'!G8 | H8: ='2. Assumptions'!H8 | I8: ='2. Assumptions'!I8 | J8: ='2. Assumptions'!J8
B9: Total Revenue | C9: =SUM(C6:C8) | D9: =SUM(D6:D8) | E9: =SUM(E6:E8) | F9: =SUM(F6:F8) | G9: =SUM(G6:G8) | H9: =SUM(H6:H8) | I9: =SUM(I6:I8) | J9: =SUM(J6:J8)
B10: Revenue growth YoY | D10: =D9/C9-1 | E10: =E9/D9-1 | F10: =F9/E9-1 | G10: =G9/F9-1 | H10: =H9/G9-1 | I10: =I9/H9-1 | J10: =J9/I9-1
B12: Gross margin % | C12: ='2. Assumptions'!C13 | D12: ='2. Assumptions'!D13 | E12: ='2. Assumptions'!E13 | F12: ='2. Assumptions'!F13 | G12: ='2. Assumptions'!G13 | H12: ='2. Assumptions'!H13 | I12: ='2. Assumptions'!I13 | J12: ='2. Assumptions'!J13
B13: Gross profit | C13: =C9*C12 | D13: =D9*D12 | E13: =E9*E12 | F13: =F9*F12 | G13: =G9*G12 | H13: =H9*H12 | I13: =I9*I12 | J13: =J9*J12
B14: Opex % of revenue | C14: ='2. Assumptions'!C14 | D14: ='2. Assumptions'!D14 | E14: ='2. Assumptions'!E14 | F14: ='2. Assumptions'!F14 | G14: ='2. Assumptions'!G14 | H14: ='2. Assumptions'!H14 | I14: ='2. Assumptions'!I14 | J14: ='2. Assumptions'!J14
B15: Opex | C15: =C9*C14 | D15: =D9*D14 | E15: =E9*E14 | F15: =F9*F14 | G15: =G9*G14 | H15: =H9*H14 | I15: =I9*I14 | J15: =J9*J14
B16: EBIT | C16: =C13-C15 | D16: =D13-D15 | E16: =E13-E15 | F16: =F13-F15 | G16: =G13-G15 | H16: =H13-H15 | I16: =I13-I15 | J16: =J13-J15
B17: EBIT margin % | C17: =C16/C9 | D17: =D16/D9 | E17: =E16/E9 | F17: =F16/F9 | G17: =G16/G9 | H17: =H16/H9 | I17: =I16/I9 | J17: =J16/J9
B19: D&A % of revenue | C19: ='2. Assumptions'!C15 | D19: ='2. Assumptions'!D15 | E19: ='2. Assumptions'!E15 | F19: ='2. Assumptions'!F15 | G19: ='2. Assumptions'!G15 | H19: ='2. Assumptions'!H15 | I19: ='2. Assumptions'!I15 | J19: ='2. Assumptions'!J15
B20: D&A | C20: =C9*C19 | D20: =D9*D19 | E20: =E9*E19 | F20: =F9*F19 | G20: =G9*G19 | H20: =H9*H19 | I20: =I9*I19 | J20: =J9*J19
B21: EBITDA | C21: =C16+C20 | D21: =D16+D20 | E21: =E16+E20 | F21: =F16+F20 | G21: =G16+G20 | H21: =H16+H20 | I21: =I16+I20 | J21: =J16+J20
B22: EBITDA margin % | C22: =C21/C9 | D22: =D21/D9 | E22: =E21/E9 | F22: =F21/F9 | G22: =G21/G9 | H22: =H21/H9 | I22: =I21/I9 | J22: =J21/J9
B24: Effective tax rate | C24: ='2. Assumptions'!C18 | D24: ='2. Assumptions'!D18 | E24: ='2. Assumptions'!E18 | F24: ='2. Assumptions'!F18 | G24: ='2. Assumptions'!G18 | H24: ='2. Assumptions'!H18 | I24: ='2. Assumptions'!I18 | J24: ='2. Assumptions'!J18
B25: Tax on EBIT | C25: =C16*C24 | D25: =D16*D24 | E25: =E16*E24 | F25: =F16*F24 | G25: =G16*G24 | H25: =H16*H24 | I25: =I16*I24 | J25: =J16*J24
B26: NOPAT | C26: =C16-C25 | D26: =D16-D25 | E26: =E16-E25 | F26: =F16-F25 | G26: =G16-G25 | H26: =H16-H25 | I26: =I16-I25 | J26: =J16-J25
B28: FCFF BUILD
B29: Capex | C29: =-C9*'2. Assumptions'!C16 | D29: =-D9*'2. Assumptions'!D16 | E29: =-E9*'2. Assumptions'!E16 | F29: =-F9*'2. Assumptions'!F16 | G29: =-G9*'2. Assumptions'!G16 | H29: =-H9*'2. Assumptions'!H16 | I29: =-I9*'2. Assumptions'!I16 | J29: =-J9*'2. Assumptions'!J16
B30: NWC change | C30: =-C9*'2. Assumptions'!C17 | D30: =-D9*'2. Assumptions'!D17 | E30: =-E9*'2. Assumptions'!E17 | F30: =-F9*'2. Assumptions'!F17 | G30: =-G9*'2. Assumptions'!G17 | H30: =-H9*'2. Assumptions'!H17 | I30: =-I9*'2. Assumptions'!I17 | J30: =-J9*'2. Assumptions'!J17
B31: FCFF | C31: =C26+C20+C29+C30 | D31: =D26+D20+D29+D30 | E31: =E26+E20+E29+E30 | F31: =F26+F20+F29+F30 | G31: =G26+G20+G29+G30 | H31: =H26+H20+H29+H30 | I31: =I26+I20+I29+I30 | J31: =J26+J20+J29+J30
B32: FCFF margin | C32: =C31/C9 | D32: =D31/D9 | E32: =E31/E9 | F32: =F31/F9 | G32: =G31/G9 | H32: =H31/H9 | I32: =I31/I9 | J32: =J31/J9

Sheet 4. DCF
B2: DISCOUNTED CASH FLOW VALUATION
C4: FY26E | D4: FY27E | E4: FY28E | F4: FY29E | G4: FY30E
B5: Year # | C5: 1 | D5: 2 | E5: 3 | F5: 4 | G5: 5
B6: Discount period (mid-year) | C6: 0.5 | D6: 1.5 | E6: 2.5 | F6: 3.5 | G6: 4.5
B7: FCFF (link from IS) | C7: ='3. Income Statement'!F31 | D7: ='3. Income Statement'!G31 | E7: ='3. Income Statement'!H31 | F7: ='3. Income Statement'!I31 | G7: ='3. Income Statement'!J31
B8: WACC | C8: ='5. WACC'!C12 | D8: =$C$8 | E8: =$C$8 | F8: =$C$8 | G8: =$C$8
B9: Discount factor | C9: =1/(1+C8)^C6 | D9: =1/(1+D8)^D6 | E9: =1/(1+E8)^E6 | F9: =1/(1+F8)^F6 | G9: =1/(1+G8)^G6
B10: PV of FCFF | C10: =C7*C9 | D10: =D7*D9 | E10: =E7*E9 | F10: =F7*F9 | G10: =G7*G9
B12: TERMINAL VALUE (Gordon growth)
B13: Terminal growth rate | C13: 0.03
B14: Terminal FCFF | C14: =G7*(1+C13)
B15: Terminal value (undiscounted) | C15: =C14/(C8-C13)
B16: PV of terminal value | C16: =C15*G9
B18: VALUATION SUMMARY
B19: Sum of PV(FCFF) | C19: =SUM(C10:G10)
B20: PV of terminal value | C20: =C16
B21: Enterprise value | C21: =C19+C20
B22: Less: Net debt (FY25) | C22: 48958
B23: Equity value | C23: =C21-C22
B24: Diluted shares (mn) | C24: 4969
B25: Implied price per share | C25: =C23/C24
B26: Spot price | C26: 422.76
B27: Implied upside / (downside) | C27: =C25/C26-1
B28: TV % of EV | C28: =C20/C21

Sheet 5. WACC
B2: WEIGHTED AVERAGE COST OF CAPITAL
B4: Risk-free rate (10Y UST) | C4: 0.0431 | D4: 10Y UST close 24-Apr-26 (Yahoo)
B5: Equity risk premium | C5: 0.05 | D5: Damodaran 2025 implied ERP
B6: Levered beta | C6: 1.2 | D6: Bloomberg 2Y weekly
B7: Pre-tax cost of debt | C7: 0.05 | D7: Senior notes blended yield
B8: Effective tax rate | C8: 0.18 | D8: AVGO 10-K FY25
B9: Target debt weight | C9: 0.15 | D9: Mgmt long-term capital structure
B11: Cost of equity (CAPM) | C11: =C4+C6*C5
B12: WACC | C12: 0.095

Sheet 6. Sensitivity
B2: DCF SENSITIVITY — IMPLIED PRICE BY WACC × TERMINAL GROWTH
B4: WACC \ g | C4: 2.0% | D4: 2.5% | E4: 3.0% | F4: 3.5% | G4: 4.0%
B5: 7.5% | C5: 536.7 | D5: 584.2 | E5: 642.3 | F5: 714.8 | G5: 808.1
B6: 8.0% | C6: 489.4 | D6: 528.3 | E6: 575.1 | F6: 632.2 | G6: 703.6
B7: 8.5% | C7: 449.4 | D7: 481.8 | E7: 520.1 | F7: 566.1 | G7: 622.3
B8: 9.0% | C8: 415.1 | D8: 442.4 | E8: 474.3 | F8: 512 | G8: 557.3
B9: 9.5% | C9: 385.4 | D9: 408.7 | E9: 435.6 | F9: 467 | G9: 504.1
B10: 10.0% | C10: 359.4 | D10: 379.5 | E10: 402.5 | F10: 429 | G10: 459.9
B11: 10.5% | C11: 336.6 | D11: 354 | E11: 373.8 | F11: 396.4 | G11: 422.4
B12: 11.0% | C12: 316.2 | D12: 331.5 | E12: 348.7 | F12: 368.1 | G12: 390.4
B13: 11.5% | C13: 298.1 | D13: 311.5 | E13: 326.6 | F13: 343.5 | G13: 362.6
B14: 12.0% | C14: 281.8 | D14: 293.7 | E14: 306.9 | F14: 321.7 | G14: 338.3

Sheet 7. Comps
B2: TRADING COMPARABLES
B4: Ticker | C4: Name | D4: Price | E4: MktCap_$B | F4: EV_$B | G4: Fwd P/E | H4: EV/Rev | I4: EV/EBITDA | J4: GM % | K4: Op M % | L4: Rev Gr % | M4: Beta
B5: AVGO | C5: Broadcom | D5: 399.83 | E5: 1893.0624 | F5: 1944.9454 | G5: 22.068169 | H5: 28.484 | I5: 52.258 | J5: 0.76725996 | K5: 0.44943002 | L5: 0.295 | M5: 1.253
B6: NVDA | C6: Nvidia | D6: 213.17 | E6: 5181.0969 | F6: 5128.8872 | G6: 18.966686 | H6: 23.752 | I6: 38.496 | J6: 0.71068 | K6: 0.65024 | L6: 0.732 | M6: 2.335
B7: AMD | C7: Advanced Micro Devices | D7: 323.21 | E7: 526.96508 | F7: 520.41908 | G7: 29.262484 | H7: 15.024 | I7: 77.156 | J7: 0.52493 | K7: 0.17059 | L7: 0.341 | M7: 1.963
B8: MRVL | C8: Marvell Technology | D8: 153.23 | E8: 133.99323 | F8: 136.12049 | G8: 28.247398 | H8: 16.611 | I8: 51.767 | J8: 0.51023996 | K8: 0.18655 | L8: 0.221 | M8: 1.822
B9: QCOM | C9: Qualcomm | D9: 150 | E9: 160.20677 | F9: 163.045 | G9: 13.614815 | H9: 3.634 | I9: 11.846 | J9: 0.55101 | K9: 0.27473 | L9: 0.05 | M9: 1.279
B10: TXN | C10: Texas Instruments | D10: 265 | E10: 241.17459 | F10: 250.12158 | G10: 28.996418 | H10: 13.566 | I10: 28.866 | J10: 0.57322 | K10: 0.37824002 | L10: 0.186 | M10: 0.994
B11: TSM | C11: Taiwan Semiconductor | D11: 392.34 | E11: 2034.8322 | F11: 7848.4629 | G11: 20.336739 | H11: 1.912 | I11: 2.748 | J11: 0.61873 | K11: 0.58105 | L11: 0.351 | M11: 1.251
B12: INTC | C12: Intel | D12: 84.52 | E12: 424.7975 | F12: 450.63451 | G12: 57.392353 | H12: 8.382 | I12: 31.793 | J12: 0.372 | K12: 0.06879 | L12: 0.072 | M12: 1.349
C14: Median (peers ex-AVGO) | D14: =MEDIAN(D6:D12) | E14: =MEDIAN(E6:E12) | F14: =MEDIAN(F6:F12) | G14: =MEDIAN(G6:G12) | H14: =MEDIAN(H6:H12) | I14: =MEDIAN(I6:I12) | J14: =MEDIAN(J6:J12) | K14: =MEDIAN(K6:K12) | ... M14: =MEDIAN(M6:M12)
B20: IMPLIED PRICE FROM PEER MULTIPLES
B22: CY27E EPS estimate ($) | C22: ='3. Income Statement'!G16*(1-'3. Income Statement'!G24)/'1. Cover'!C12
B23: Target Fwd P/E (low) | C23: 18
B24: Target Fwd P/E (mid) | C24: 22
B25: Target Fwd P/E (high) | C25: 26
B26: Implied price (low) | C26: =C22*C23
B27: Implied price (mid) | C27: =C22*C24
B28: Implied price (high) | C28: =C22*C25

Sheet 8. SOTP
A1: Blended EBITDA margin FY25A = 67.7%; Software revenue weight = 37.4%; Semi revenue weight = 62.6%
A2: If software EBITDA margin = 77% (Broadcom upper-bound), implied semi EBITDA margin = 62.0% | B2: SUM-OF-THE-PARTS (FY27E)
B4: Segment | C4: FY27E Rev ($mn) | D4: EBITDA Margin | E4: FY27E EBITDA | F4: EV Mult Low | G4: EV Mult Mid | H4: EV Mult High
B5: Semiconductor Solutions | C5: ='2. Assumptions'!G6+'2. Assumptions'!G7 | D5: 0.62 | E5: =C5*D5 | F5: 16 | G5: 20 | H5: 24
B6: Infrastructure Software | C6: ='2. Assumptions'!G8 | D6: 0.77 | E6: =C6*D6 | F6: 14 | G6: 17 | H6: 20
B8: Total EV ($mn) | F8: =E5*F5+E6*F6 | G8: =E5*G5+E6*G6 | H8: =E5*H5+E6*H6
B9: Less: Net debt | F9: 48958 | G9: 48958 | H9: 48958
B10: Equity value | F10: =F8-F9 | G10: =G8-G9 | H10: =H8-H9
B11: Diluted shares (mn) | F11: 4969 | G11: 4969 | H11: 4969
B12: Implied price per share | F12: =F10/F11 | G12: =G10/G11 | H12: =H10/H11

Sheet 9. Monte Carlo
B2: MONTE CARLO SIMULATION SUMMARY
B3: 10,000 paths • Drivers in scripts/02_valuation.py
B5: Mean intrinsic price | C5: 470.92811
B6: Median | C6: 456.05096
B7: 25th percentile (P25) | C7: 378.25734
B8: 75th percentile (P75) | C8: 543.79764
B9: Probability(intrinsic > spot) | C9: 0.68349359
B12: Driver distribution (assumed Normal)
B13: FY27 AI revenue ($B) | C13: ~ N(125, 25)
B14: AI growth FY27→FY30 CAGR | C14: ~ N(30%, 10%)
B15: Terminal growth rate | C15: ~ N(3.0%, 0.5%)
B16: WACC | C16: ~ N(base WACC, 0.5%)
B17: Steady-state EBITDA margin | C17: ~ N(68.5%, 2.5%)
B18: Capex / Sales | C18: ~ N(1.1%, 0.3%)
B19: Non-AI semi growth | C19: ~ N(4%, 2%)
B20: Software growth | C20: ~ N(7%, 2.5%)

Sheet 10. Football Field
B2: VALUATION SYNTHESIS — FOOTBALL FIELD
B4: Method | C4: Low | D4: Mid | E4: High | F4: Implied Upside (Mid)
B5: DCF (5Y FCFF + Gordon TV) | C5: 402.5 | D5: ='4. DCF'!C25 | E5: 474.3 | F5: =D5/'1. Cover'!C8-1
B6: SOTP (FY27E EV/EBITDA) | C6: 320.92212 | D6: 401.21393 | E6: 481.50574 | F6: =D6/'1. Cover'!C8-1
B7: Trading Comps (Fwd P/E) | C7: 360 | D7: 440 | E7: 520 | F7: =D7/'1. Cover'!C8-1
B8: Trading Comps (EV/EBITDA) | C8: 316.21292 | D8: 409.37452 | E8: 502.53612 | F8: =D8/'1. Cover'!C8-1
B9: Monte Carlo (P25/Median/P75) | C9: 378.25734 | D9: 456.05096 | E9: 543.79764 | F9: =D9/422.76-1
B10: Street Consensus (last 30D) | C10: 430 | D10: 469 | E10: 500 | F10: =D10/422.76-1
B12: Average | C12: =AVERAGE(C5:C10) | D12: =AVERAGE(D5:D10) | E12: =AVERAGE(E5:E10)
B14: Spot price | C14: ='1. Cover'!C8
B15: Recommendation | C15: BUY
